odoo/addons/website_sale_stock_product_matrix/README.rst
odoo/addons/website_sale_stock_product_matrix/__init__.py
odoo/addons/website_sale_stock_product_matrix/__manifest__.py
odoo/addons/website_sale_stock_product_matrix/i18n/es.po
odoo/addons/website_sale_stock_product_matrix/i18n/it.po
odoo/addons/website_sale_stock_product_matrix/i18n/website_sale_stock_product_matrix.pot
odoo/addons/website_sale_stock_product_matrix/readme/CONTRIBUTORS.md
odoo/addons/website_sale_stock_product_matrix/readme/DESCRIPTION.md
odoo/addons/website_sale_stock_product_matrix/readme/USAGE.md
odoo/addons/website_sale_stock_product_matrix/static/description/icon.png
odoo/addons/website_sale_stock_product_matrix/static/description/index.html
odoo/addons/website_sale_stock_product_matrix/templates/product_template.xml
odoo_addon_website_sale_stock_product_matrix-17.0.1.0.0.4.dist-info/METADATA
odoo_addon_website_sale_stock_product_matrix-17.0.1.0.0.4.dist-info/WHEEL
odoo_addon_website_sale_stock_product_matrix-17.0.1.0.0.4.dist-info/top_level.txt
odoo_addon_website_sale_stock_product_matrix-17.0.1.0.0.4.dist-info/RECORD
